auxfuncs/__init__.py
auxfuncs/auxfuncs.py
auxfuncs-0.1.2.dist-info/LICENSE
auxfuncs-0.1.2.dist-info/METADATA
auxfuncs-0.1.2.dist-info/WHEEL
auxfuncs-0.1.2.dist-info/top_level.txt
auxfuncs-0.1.2.dist-info/RECORD
